[
    {
        "name": "Openlane"
    },
    {
        "name": "Yearin"
    },
    {
        "name": "Goodsilron"
    },
    {
        "name": "Condax"
    },
    {
        "name": "Opentech"
    },
    {
        "name": "Golddex"
    },
    {
        "name": "year-job"
    },
    {
        "name": "Isdom"
    },
    {
        "name": "Gogozoom"
    },
    {
        "name": "Y-corporation"
    },
    {
        "name": "Nam-zim"
    },
    {
        "name": "Donquadtech"
    },
    {
        "name": "Warephase"
    },
    {
        "name": "Donware"
    },
    {
        "name": "Faxquote"
    },
    {
        "name": "Sunnamplex"
    },
    {
        "name": "Lexiqvolax"
    },
    {
        "name": "Sumace"
    },
    {
        "name": "Treequote"
    },
    {
        "name": "Iselectrics"
    },
    {
        "name": "Zencorporation"
    },
    {
        "name": "Plusstrip"
    },
    {
        "name": "dambase"
    },
    {
        "name": "Toughzap"
    },
    {
        "name": "Codehow"
    },
    {
        "name": "Zotware"
    },
    {
        "name": "Statholdings"
    },
    {
        "name": "Conecom"
    },
    {
        "name": "Zathunicon"
    },
    {
        "name": "Labdrill"
    },
    {
        "name": "Ron-tech"
    },
    {
        "name": "Green-Plus"
    },
    {
        "name": "Groovestreet"
    },
    {
        "name": "Zoomit"
    },
    {
        "name": "Bioplex"
    },
    {
        "name": "Zumgoity"
    },
    {
        "name": "Scotfind"
    },
    {
        "name": "Dalttechnology"
    },
    {
        "name": "Kinnamplus"
    },
    {
        "name": "Konex"
    },
    {
        "name": "Stanredtax"
    },
    {
        "name": "Cancity"
    },
    {
        "name": "Finhigh"
    },
    {
        "name": "Kan-code"
    },
    {
        "name": "Blackzim"
    },
    {
        "name": "Dontechi"
    },
    {
        "name": "Xx-zobam"
    },
    {
        "name": "Fasehatice"
    },
    {
        "name": "Hatfan"
    },
    {
        "name": "Streethex"
    },
    {
        "name": "Inity"
    },
    {
        "name": "Konmatfix"
    },
    {
        "name": "Bioholding"
    },
    {
        "name": "Hottechi"
    },
    {
        "name": "Ganjaflex"
    },
    {
        "name": "Betatech"
    },
    {
        "name": "Domzoom"
    },
    {
        "name": "Ontomedia"
    },
    {
        "name": "Newex"
    },
    {
        "name": "Betasoloin"
    },
    {
        "name": "Mathtouch"
    },
    {
        "name": "Rantouch"
    },
    {
        "name": "Silis"
    },
    {
        "name": "Plussunin"
    },
    {
        "name": "Plexzap"
    },
    {
        "name": "Finjob"
    },
    {
        "name": "Xx-holding"
    },
    {
        "name": "Scottech"
    },
    {
        "name": "Funholding"
    },
    {
        "name": "Sonron"
    },
    {
        "name": "Singletechno"
    },
    {
        "name": "Rangreen"
    },
    {
        "name": "J-Texon"
    },
    {
        "name": "Rundofase"
    },
    {
        "name": "Doncon"
    }
]